gondola/__init__.py
gondola/calibration.py
gondola/db.py
gondola/events.py
gondola/gaps_flight.db
gondola/gondola_core.abi3.so
gondola/io/__init__.py
gondola/io/streamers.py
gondola/reconstruction/__init__.py
gondola/tof/__init__.py
gondola/tof/analysis.py
gondola/tracker/__init__.py
gondola/tracker/analysis.py
gondola/visual/__init__.py
gondola/visual/tof.py
gondola/visual/tracker.py
gondola-0.12.7.dist-info/METADATA
gondola-0.12.7.dist-info/WHEEL
gondola-0.12.7.dist-info/RECORD
