Metadata-Version: 2.4
Name: gondola
Version: 0.12.7
Requires-Dist: tqdm>=4.0
Requires-Dist: numpy>=2.3
Requires-Dist: matplotlib>=3.10
Requires-Dist: charmingbeauty>=0.1
Requires-Dist: pydashi>=2
Requires-Dist: cmocean>=4
Requires-Dist: loguru>=0.7
Requires-Dist: vtk>=9
Requires-Dist: iminuit>=2
Requires-Dist: polars>=1.33
Requires-Dist: pyzmq>=27
Requires-Dist: twine>=6.2.0
Summary: GAPS Online and Offline Analysis software
Author-email: "J.A.Stoessl, G.Tytus" <stoessl@hawaii.edu>
License: GPLV3
Requires-Python: >=3.11
Project-URL: Documentation, https://gaps-collab.github.io/gaps-online-software/
Project-URL: Homepage, https://github.com/GAPS-Collab/gaps-online-software
Project-URL: Repository, https://github.com/GAPS-Collab/gaps-online-software
